sojourner/__init__.py
sojourner/_modidx.py
sojourner/cli.py
sojourner/core.py
sojourner-0.0.6.dist-info/LICENSE
sojourner-0.0.6.dist-info/METADATA
sojourner-0.0.6.dist-info/WHEEL
sojourner-0.0.6.dist-info/entry_points.txt
sojourner-0.0.6.dist-info/top_level.txt
sojourner-0.0.6.dist-info/RECORD
