Metadata-Version: 2.1
Name: sojourner
Version: 0.0.6
Summary: a minimal tool for managing client data stored in GCP
Home-page: https://github.com/withmartian/sojourner
Author: shy
Author-email: sasha@withmartian.com
License: Apache Software License 2.0
Keywords: nbdev jupyter notebook python
Classifier: Development Status :: 4 - Beta
Classifier: Intended Audience :: Developers
Classifier: Natural Language :: English
Classifier: Programming Language :: Python :: 3.7
Classifier: Programming Language :: Python :: 3.8
Classifier: Programming Language :: Python :: 3.9
Classifier: Programming Language :: Python :: 3.10
Classifier: License :: OSI Approved :: Apache Software License
Requires-Python: >=3.7
License-File: LICENSE
Requires-Dist: click
Requires-Dist: google-cloud-storage
Requires-Dist: pydantic
Requires-Dist: python-dotenv
Provides-Extra: dev
Requires-Dist: nbdev; extra == "dev"
Requires-Dist: pre-commit; extra == "dev"
Requires-Dist: setuptools; extra == "dev"
